{
 "bio": "An auto driver, Manikam, desperately tries to hide his dark underworld side to keep his promise to his father.", 
 "name": "Baasha", 
 "language": [
  "Tamil", 
  "Telugu", 
  "Hindi"
 ], 
 "country": [
  "India"
 ], 
 "director": [
  "Suresh Krishna"
 ], 
 "poster": "https://www.imdb.com/title/tt0139876/mediaviewer/rm2556644608", 
 "genre": [
  "Action", 
  "Crime", 
  "Drama"
 ], 
 "runtime": "145 min", 
 "caste": [
  {
   "imbd id": "nm0707425", 
   "imbd name": "Rajinikanth"
  }, 
  {
   "imbd id": "nm0619324", 
   "imbd name": "Nagma"
  }, 
  {
   "imbd id": "nm0706499", 
   "imbd name": "Raghuvaran"
  }, 
  {
   "imbd id": "nm0897206", 
   "imbd name": "Vijayakumar"
  }, 
  {
   "imbd id": "nm0417301", 
   "imbd name": "Janagaraj"
  }, 
  {
   "imbd id": "nm0222181", 
   "imbd name": "Devan"
  }, 
  {
   "imbd id": "nm1686962", 
   "imbd name": "Anandraj"
  }, 
  {
   "imbd id": "nm3161240", 
   "imbd name": "Sasikumar"
  }, 
  {
   "imbd id": "nm3118248", 
   "imbd name": "Sathyapriya"
  }, 
  {
   "imbd id": "nm0951193", 
   "imbd name": "Yuvarani"
  }, 
  {
   "imbd id": "nm0707270", 
   "imbd name": "Charan Raj"
  }, 
  {
   "imbd id": "nm6342165", 
   "imbd name": "Shenbaga"
  }, 
  {
   "imbd id": "nm0471430", 
   "imbd name": "Raja Krishnamoorthy"
  }, 
  {
   "imbd id": "nm1302977", 
   "imbd name": "Sethu Vinayakam"
  }, 
  {
   "imbd id": "nm1688033", 
   "imbd name": "Kavithalaya Krishnan"
  }
 ]
}