{
 "bio": "Three inseparable childhood friends are just out of college. Nothing comes between them - until they each fall in love, and their wildly different approaches to relationships creates tension.", 
 "name": "DilChahtaHai", 
 "language": [
  "Hindi", 
  "English", 
  "Urdu"
 ], 
 "country": [
  "India"
 ], 
 "director": [
  "Farhan Akhtar"
 ], 
 "poster": "https://www.imdb.com/title/tt0292490/mediaviewer/rm610798080", 
 "genre": [
  "Comedy", 
  "Drama", 
  "Romance"
 ], 
 "runtime": "183 min", 
 "caste": [
  {
   "imbd id": "nm0451148", 
   "imbd name": "Aamir Khan"
  }, 
  {
   "imbd id": "nm0451307", 
   "imbd name": "Saif Ali Khan"
  }, 
  {
   "imbd id": "nm0451379", 
   "imbd name": "Akshaye Khanna"
  }, 
  {
   "imbd id": "nm0006689", 
   "imbd name": "Preity Zinta"
  }, 
  {
   "imbd id": "nm0006764", 
   "imbd name": "Sonali Kulkarni"
  }, 
  {
   "imbd id": "nm0438092", 
   "imbd name": "Dimple Kapadia"
  }, 
  {
   "imbd id": "nm0451183", 
   "imbd name": "Ayub Khan"
  }, 
  {
   "imbd id": "nm0438494", 
   "imbd name": "Rajat Kapoor"
  }, 
  {
   "imbd id": "nm0611663", 
   "imbd name": "Suhasini Mulay"
  }, 
  {
   "imbd id": "nm0451156", 
   "imbd name": "Ahmed Khan"
  }, 
  {
   "imbd id": "nm0683496", 
   "imbd name": "Suchitra Pillai"
  }, 
  {
   "imbd id": "nm1223423", 
   "imbd name": "Anjula Bedi"
  }, 
  {
   "imbd id": "nm0659244", 
   "imbd name": "Rakesh Pandey"
  }, 
  {
   "imbd id": "nm1332585", 
   "imbd name": "Samantha Tremayne"
  }, 
  {
   "imbd id": "nm8631679", 
   "imbd name": "Claire"
  }
 ]
}