[
 {
  "imbd name": "Amol Palekar", 
  "imbd id": "nm0657505"
 }, 
 {
  "imbd name": "Bindiya Goswami", 
  "imbd id": "nm0331727"
 }, 
 {
  "imbd name": "Deven Verma", 
  "imbd id": "nm0894340"
 }, 
 {
  "imbd name": "Shubha Khote", 
  "imbd id": "nm0451863"
 }, 
 {
  "imbd name": "Manju Singh", 
  "imbd id": "nm1542933"
 }, 
 {
  "imbd name": "Dina Pathak", 
  "imbd id": "nm0665544"
 }, 
 {
  "imbd name": "Pushpa", 
  "imbd id": "nm0701106"
 }, 
 {
  "imbd name": "David Abraham", 
  "imbd id": "nm0008932"
 }, 
 {
  "imbd name": "Yunus Parvez", 
  "imbd id": "nm0664109"
 }, 
 {
  "imbd name": "Utpal Dutt", 
  "imbd id": "nm0244884"
 }, 
 {
  "imbd name": "Ashwani", 
  "imbd id": "nm1538133"
 }, 
 {
  "imbd name": "Harish Magon", 
  "imbd id": "nm1442040"
 }, 
 {
  "imbd name": "Bhola", 
  "imbd id": "nm0080410"
 }, 
 {
  "imbd name": "Amol Sen", 
  "imbd id": "nm1059411"
 }, 
 {
  "imbd name": "Siddharth", 
  "imbd id": "nm1193461"
 }
]