[
 {
  "imbd name": "Abhay Deol", 
  "imbd id": "nm1867717"
 }, 
 {
  "imbd name": "Paresh Rawal", 
  "imbd id": "nm0712546"
 }, 
 {
  "imbd name": "Neetu Chandra", 
  "imbd id": "nm1911617"
 }, 
 {
  "imbd name": "Archana Puran Singh", 
  "imbd id": "nm0700687"
 }, 
 {
  "imbd name": "Manu Rishi Chadha", 
  "imbd id": "nm2286188"
 }, 
 {
  "imbd name": "Richa Chadha", 
  "imbd id": "nm3190246"
 }, 
 {
  "imbd name": "Manjot Singh", 
  "imbd id": "nm3190972"
 }, 
 {
  "imbd name": "Anurag Arora", 
  "imbd id": "nm3189957"
 }, 
 {
  "imbd name": "Amandeep Singh Bakshi", 
  "imbd id": "nm3464267"
 }, 
 {
  "imbd name": "Rajendra Sethi", 
  "imbd id": "nm1217893"
 }, 
 {
  "imbd name": "Rajeev Ailabadi", 
  "imbd id": "nm3463739"
 }, 
 {
  "imbd name": "Nutan Surya", 
  "imbd id": "nm3464457"
 }, 
 {
  "imbd name": "Gurmeet Singh", 
  "imbd id": "nm3465021"
 }, 
 {
  "imbd name": "Ramandeep", 
  "imbd id": "nm3464512"
 }, 
 {
  "imbd name": "Nanki Singh", 
  "imbd id": "nm3464085"
 }
]