[
 {
  "imbd name": "Partho A. Gupte", 
  "imbd id": "nm4428422"
 }, 
 {
  "imbd name": "Numaan Sheikh", 
  "imbd id": "nm4473016"
 }, 
 {
  "imbd name": "Abhishek Reddy", 
  "imbd id": "nm4473026"
 }, 
 {
  "imbd name": "Sai Shara Shetty", 
  "imbd id": "nm4474558"
 }, 
 {
  "imbd name": "Monty Sarkar", 
  "imbd id": "nm4472448"
 }, 
 {
  "imbd name": "Leo Crasto", 
  "imbd id": "nm4474306"
 }, 
 {
  "imbd name": "Tijo Thomas", 
  "imbd id": "nm4475116"
 }, 
 {
  "imbd name": "Ganesh Pujari", 
  "imbd id": "nm3003545"
 }, 
 {
  "imbd name": "Walter D'Souza", 
  "imbd id": "nm4472409"
 }, 
 {
  "imbd name": "Divya Dutta", 
  "imbd id": "nm0244890"
 }, 
 {
  "imbd name": "Divya Jagdale", 
  "imbd id": "nm0415555"
 }, 
 {
  "imbd name": "Raj Zutshi", 
  "imbd id": "nm0958861"
 }, 
 {
  "imbd name": "Rahul Singh", 
  "imbd id": "nm0536799"
 }, 
 {
  "imbd name": "Aditya Lakhia", 
  "imbd id": "nm1004575"
 }, 
 {
  "imbd name": "Shashank Shende", 
  "imbd id": "nm3583019"
 }
]