[
 {
  "imbd name": "Mahesh Babu", 
  "imbd id": "nm1121870"
 }, 
 {
  "imbd name": "Kriti Sanon", 
  "imbd id": "nm5305841"
 }, 
 {
  "imbd name": "Nassar", 
  "imbd id": "nm0621937"
 }, 
 {
  "imbd name": "Pradeep Singh Rawat", 
  "imbd id": "nm1004887"
 }, 
 {
  "imbd name": "Anu Hassan", 
  "imbd id": "nm5958983"
 }, 
 {
  "imbd name": "Kelly Dorji", 
  "imbd id": "nm1795256"
 }, 
 {
  "imbd name": "Sayaji Shinde", 
  "imbd id": "nm0793851"
 }, 
 {
  "imbd name": "Krishna Murali Posani", 
  "imbd id": "nm0692586"
 }, 
 {
  "imbd name": "Srinivasa Reddy", 
  "imbd id": "nm2210188"
 }, 
 {
  "imbd name": "Ravi Verma", 
  "imbd id": "nm2637065"
 }, 
 {
  "imbd name": "Anand", 
  "imbd id": "nm0025606"
 }, 
 {
  "imbd name": "Supreeth Reddy", 
  "imbd id": "nm5036526"
 }, 
 {
  "imbd name": "Sophiya Chaudhary", 
  "imbd id": "nm1862678"
 }, 
 {
  "imbd name": "Gautham Ghattamaneni", 
  "imbd id": "nm6169009"
 }, 
 {
  "imbd name": "Hayley Joanne Bacon", 
  "imbd id": "nm5153714"
 }
]